{
  "version": "7",
  "dialect": "postgresql",
  "entries": [
    {
      "idx": 0,
      "version": "7",
      "when": 1781967631031,
      "tag": "0000_brainy_omega_red",
      "breakpoints": true
    },
    {
      "idx": 1,
      "version": "7",
      "when": 1781977983405,
      "tag": "0001_superb_raider",
      "breakpoints": true
    },
    {
      "idx": 2,
      "version": "7",
      "when": 1782035323551,
      "tag": "0002_long_puff_adder",
      "breakpoints": true
    },
    {
      "idx": 3,
      "version": "7",
      "when": 1782038441877,
      "tag": "0003_peaceful_amazoness",
      "breakpoints": true
    },
    {
      "idx": 4,
      "version": "7",
      "when": 1782303520895,
      "tag": "0004_gifted_the_order",
      "breakpoints": true
    },
    {
      "idx": 5,
      "version": "7",
      "when": 1782383359373,
      "tag": "0005_jittery_franklin_storm",
      "breakpoints": true
    },
    {
      "idx": 6,
      "version": "7",
      "when": 1782399596627,
      "tag": "0006_lying_virginia_dare",
      "breakpoints": true
    },
    {
      "idx": 7,
      "version": "7",
      "when": 1782399710371,
      "tag": "0007_flawless_inertia",
      "breakpoints": true
    },
    {
      "idx": 8,
      "version": "7",
      "when": 1782826028114,
      "tag": "0008_goofy_swarm",
      "breakpoints": true
    },
    {
      "idx": 9,
      "version": "7",
      "when": 1783172969369,
      "tag": "0009_equal_george_stacy",
      "breakpoints": true
    }
  ]
}